warframe_market/__init__.py
warframe_market/client.py
warframe_market/utils.py
warframe_market/api/__init__.py
warframe_market/api/item.py
warframe_market/api/lich.py
warframe_market/api/misc.py
warframe_market/api/order.py
warframe_market/api/riven.py
warframe_market/api/sister.py
warframe_market/api/user.py
warframe_market/common/__init__.py
warframe_market/common/base.py
warframe_market/common/enums.py
warframe_market/common/options.py
warframe_market/models/__init__.py
warframe_market/models/achievement.py
warframe_market/models/activity.py
warframe_market/models/item.py
warframe_market/models/lich.py
warframe_market/models/location.py
warframe_market/models/mission.py
warframe_market/models/npc.py
warframe_market/models/order.py
warframe_market/models/riven.py
warframe_market/models/sister.py
warframe_market/models/user.py
warframe_market/models/user_private.py
warframe_market_py-1.0.4.dist-info/METADATA
warframe_market_py-1.0.4.dist-info/WHEEL
warframe_market_py-1.0.4.dist-info/licenses/LICENSE
warframe_market_py-1.0.4.dist-info/RECORD
