Metadata-Version: 2.4
Name: warframe-market.py
Version: 1.0.4
Summary: An asynchronous Python wrapper for Warframe.Market API
Project-URL: Homepage, https://github.com/aldi-f/warframe-market.py
Author: aldi-f
License-File: LICENSE
Requires-Python: >=3.9
Requires-Dist: aiohttp==3.12.6
Requires-Dist: msgspec==0.19.0
